videomonkey/__init__.py
videomonkey/cli.py
videomonkey/main.py
videomonkey/version.py
videomonkey-0.1.0.dist-info/METADATA
videomonkey-0.1.0.dist-info/WHEEL
videomonkey-0.1.0.dist-info/entry_points.txt
videomonkey-0.1.0.dist-info/top_level.txt
videomonkey-0.1.0.dist-info/RECORD
